siswrapper/__init__.py
siswrapper/_version.py
siswrapper/siswrapper.py
siswrapper-1.2.2.dist-info/METADATA
siswrapper-1.2.2.dist-info/RECORD
siswrapper-1.2.2.dist-info/WHEEL
siswrapper-1.2.2.dist-info/top_level.txt
