Metadata-Version: 2.1
Name: siswrapper
Version: 1.2.2
Summary: A Python wrapper for SIS
Home-page: https://github.com/mario33881/siswrapper
Author: Zenaro Stefano (mario33881)
Author-email: mariortgasd@hotmail.com
License: MIT
Keywords: SIS BLIF siswrapper wrapper development
Platform: UNKNOWN
Classifier: Development Status :: 5 - Production/Stable
Classifier: Intended Audience :: Developers
Classifier: Topic :: Software Development
Classifier: Topic :: Software Development :: Libraries :: Python Modules
Classifier: License :: OSI Approved :: MIT License
Classifier: Programming Language :: Python :: 3
Classifier: Operating System :: Unix
Requires-Python: >=3
Requires-Dist: pexpect (==4.8.0)
